opg_sirius_service/__init__.py
opg_sirius_service/sirius_handler.py
opg_sirius_service-2.1.1.dist-info/LICENSE
opg_sirius_service-2.1.1.dist-info/METADATA
opg_sirius_service-2.1.1.dist-info/WHEEL
opg_sirius_service-2.1.1.dist-info/top_level.txt
opg_sirius_service-2.1.1.dist-info/RECORD
