Metadata-Version: 2.1
Name: opg-sirius-service
Version: 2.1.1
Summary: Sirius Service
Home-page: https://github.com/ministryofjustice/opg-data
Author: OPG
Author-email: opg-integrations@digital.justice.gov.uk
Classifier: Programming Language :: Python :: 3
Classifier: License :: OSI Approved :: MIT License
Classifier: Operating System :: OS Independent
Requires-Python: >=3.8
License-File: LICENSE
Requires-Dist: boto3
Requires-Dist: requests-aws4auth (==1.0.1)
Requires-Dist: pyjwt (==2.4.0)
